da2package/__init__.py
da2package/module.py
da2package/my_module.py
da2package-0.0.4a0.dist-info/LICENSE
da2package-0.0.4a0.dist-info/METADATA
da2package-0.0.4a0.dist-info/WHEEL
da2package-0.0.4a0.dist-info/top_level.txt
da2package-0.0.4a0.dist-info/RECORD
